odoo9_addon_openeducat_timetable-9.0.2.4.0-py2.7-nspkg.pth
odoo_addons/openeducat_timetable/__openerp__.py
odoo_addons/openeducat_timetable/__init__.py
odoo_addons/openeducat_timetable/timetable_menu.xml
odoo_addons/openeducat_timetable/security/ir.model.access.csv
odoo_addons/openeducat_timetable/report/report_timetable_teacher_generate.xml
odoo_addons/openeducat_timetable/report/timetable_report_student.py
odoo_addons/openeducat_timetable/report/report_timetable_student_generate.xml
odoo_addons/openeducat_timetable/report/__init__.py
odoo_addons/openeducat_timetable/report/timetable_report_teacher.py
odoo_addons/openeducat_timetable/report/report_menu.xml
odoo_addons/openeducat_timetable/dashboard/timetable_faculty_dashboard.xml
odoo_addons/openeducat_timetable/dashboard/timetable_student_dashboard.xml
odoo_addons/openeducat_timetable/models/__init__.py
odoo_addons/openeducat_timetable/models/period.py
odoo_addons/openeducat_timetable/models/faculty.py
odoo_addons/openeducat_timetable/models/timetable.py
odoo_addons/openeducat_timetable/i18n/openeducat_timetable.pot
odoo_addons/openeducat_timetable/wizard/generate_timetable_view.xml
odoo_addons/openeducat_timetable/wizard/time_table_report.py
odoo_addons/openeducat_timetable/wizard/__init__.py
odoo_addons/openeducat_timetable/wizard/generate_timetable.py
odoo_addons/openeducat_timetable/wizard/time_table_report.xml
odoo_addons/openeducat_timetable/views/period_view.xml
odoo_addons/openeducat_timetable/views/faculty_view.xml
odoo_addons/openeducat_timetable/views/timetable_view.xml
odoo_addons/openeducat_timetable/demo/op.period.csv
odoo_addons/openeducat_timetable/demo/op_timetable_demo.xml
odoo_addons/openeducat_timetable/static/description/openeducat_logo.png
odoo_addons/openeducat_timetable/static/description/generate_timetable.png
odoo_addons/openeducat_timetable/static/description/index.html
odoo_addons/openeducat_timetable/static/description/timetable.png
odoo9_addon_openeducat_timetable-9.0.2.4.0.dist-info/top_level.txt
odoo9_addon_openeducat_timetable-9.0.2.4.0.dist-info/WHEEL
odoo9_addon_openeducat_timetable-9.0.2.4.0.dist-info/RECORD
odoo9_addon_openeducat_timetable-9.0.2.4.0.dist-info/metadata.json
odoo9_addon_openeducat_timetable-9.0.2.4.0.dist-info/DESCRIPTION.rst
odoo9_addon_openeducat_timetable-9.0.2.4.0.dist-info/METADATA
odoo9_addon_openeducat_timetable-9.0.2.4.0.dist-info/namespace_packages.txt
